pyheartbeat/__init__.py
pyheartbeat/heartbeat_library.py
pyheartbeat-0.0.11.dist-info/LICENSE
pyheartbeat-0.0.11.dist-info/METADATA
pyheartbeat-0.0.11.dist-info/WHEEL
pyheartbeat-0.0.11.dist-info/top_level.txt
pyheartbeat-0.0.11.dist-info/RECORD
