Metadata-Version: 2.2
Name: pyheartbeat
Version: 0.0.11
Summary: Library for sending pulses to a process monitoring server
Author: Pedro Ferreira Braz
Author-email: pbraz.pedrof@gmail.com
License: MIT License
Keywords: pyheartbeat,heartbeat_library,heartbeat,heartbeat-library,heartbeat-api,heartbeat-wrapper,heartbeat-python,heartbeat-python-wrapper,heartbeat-python-api,heartbeat-python-wrapper-api,heartbeat-python-api-wrapper,multithreading,threading,requests,python-requests,python-threading,python-multithreading,python-heartbeat,python-heartbeat-api,python-heartbeat-wrapper,python-heartbeat-python,python-heartbeat-python-wrapper,python-heartbeat-python-api,python-heartbeat-python-wrapper-api,python-
License-File: LICENSE
Requires-Dist: requests
Requires-Dist: apscheduler
Dynamic: author
Dynamic: author-email
Dynamic: description
Dynamic: description-content-type
Dynamic: keywords
Dynamic: license
Dynamic: requires-dist
Dynamic: summary
